nilva_django_auth/__init__.py
nilva_django_auth/admin.py
nilva_django_auth/apps.py
nilva_django_auth/models.py
nilva_django_auth/serializers.py
nilva_django_auth/session_management.py
nilva_django_auth/settings.py
nilva_django_auth/urls.py
nilva_django_auth/views.py
nilva_django_auth/locale/fa/LC_MESSAGES/django.mo
nilva_django_auth/locale/fa/LC_MESSAGES/django.po
nilva_django_auth/migrations/0001_initial.py
nilva_django_auth/migrations/__init__.py
nilva_django_auth/simplejwt/__init__.py
nilva_django_auth/simplejwt/authentication.py
nilva_django_auth/simplejwt/backends.py
nilva_django_auth/simplejwt/compat.py
nilva_django_auth/simplejwt/exceptions.py
nilva_django_auth/simplejwt/models.py
nilva_django_auth/simplejwt/serializers.py
nilva_django_auth/simplejwt/settings.py
nilva_django_auth/simplejwt/state.py
nilva_django_auth/simplejwt/tokens.py
nilva_django_auth/simplejwt/utils.py
nilva_django_auth/simplejwt/views.py
nilva_django_auth-0.2.0.dist-info/licenses/LICENSE
nilva_django_auth-0.2.0.dist-info/METADATA
nilva_django_auth-0.2.0.dist-info/WHEEL
nilva_django_auth-0.2.0.dist-info/top_level.txt
nilva_django_auth-0.2.0.dist-info/RECORD
