Metadata-Version: 2.4
Name: nilva-django-auth
Version: 0.2.0
Summary: A Django authentication package using DRF and JWT tokens
Author-email: mhmdreza <mrezajafarzade98@gmail.com>
License-Expression: MIT
Project-URL: homepage, https://github.com/nilva/nilva-django-auth
Project-URL: repository, https://github.com/nilva/nilva-django-auth
Classifier: Programming Language :: Python :: 3
Classifier: Operating System :: OS Independent
Classifier: Framework :: Django
Classifier: Framework :: Django :: 3.2
Classifier: Framework :: Django :: 4.0
Classifier: Framework :: Django :: 4.1
Classifier: Framework :: Django :: 4.2
Requires-Python: >=3.10
License-File: LICENSE
Requires-Dist: django>=3.2
Requires-Dist: djangorestframework>=3.12.0
Requires-Dist: user-agents==2.2.0
Requires-Dist: PyJWT>=2.0.0
Provides-Extra: dev
Requires-Dist: pytest>=7.0.0; extra == "dev"
Requires-Dist: pytest-django>=4.5.0; extra == "dev"
Requires-Dist: pytest-cov>=4.1.0; extra == "dev"
Requires-Dist: drf-yasg>=1.21.0; extra == "dev"
Requires-Dist: black>=23.0.0; extra == "dev"
Requires-Dist: isort>=5.10.0; extra == "dev"
Requires-Dist: setuptools; extra == "dev"
Dynamic: license-file
